markpub_themes/__init__.py
markpub_themes/cli.py
markpub_themes/themes/__init__.py
markpub_themes/themes/dolce/LICENSE
markpub_themes/themes/dolce/README.md
markpub_themes/themes/dolce/__init__.py
markpub_themes/themes/dolce/_footer.html
markpub_themes/themes/dolce/_header.html
markpub_themes/themes/dolce/_javascript.html
markpub_themes/themes/dolce/all-pages.html
markpub_themes/themes/dolce/page.html
markpub_themes/themes/dolce/recent-pages.html
markpub_themes/themes/dolce/search.html
markpub_themes/themes/dolce/static/markpub_static/css/custom.css
markpub_themes/themes/dolce/static/markpub_static/css/style.css
markpub_themes/themes/dolce/static/markpub_static/js/script.js
markpub_themes/themes/elysium/LICENSE
markpub_themes/themes/elysium/README.md
markpub_themes/themes/elysium/__init__.py
markpub_themes/themes/elysium/_body-header.html
markpub_themes/themes/elysium/_footer.html
markpub_themes/themes/elysium/_header.html
markpub_themes/themes/elysium/_javascript.html
markpub_themes/themes/elysium/all-pages.html
markpub_themes/themes/elysium/page.html
markpub_themes/themes/elysium/recent-pages.html
markpub_themes/themes/elysium/search.html
markpub_themes/themes/elysium/static/markpub_static/css/custom.css
markpub_themes/themes/elysium/static/markpub_static/css/style.css
markpub_themes/themes/elysium/static/markpub_static/js/script.js
markpub_themes/themes/forte/LICENSE
markpub_themes/themes/forte/README.md
markpub_themes/themes/forte/__init__.py
markpub_themes/themes/forte/_body-header.html
markpub_themes/themes/forte/_footer.html
markpub_themes/themes/forte/_header.html
markpub_themes/themes/forte/_javascript.html
markpub_themes/themes/forte/all-pages.html
markpub_themes/themes/forte/page.html
markpub_themes/themes/forte/recent-pages.html
markpub_themes/themes/forte/search.html
markpub_themes/themes/forte/static/markpub_static/css/custom.css
markpub_themes/themes/forte/static/markpub_static/css/forte.css
markpub_themes-2.1.2.dist-info/METADATA
markpub_themes-2.1.2.dist-info/WHEEL
markpub_themes-2.1.2.dist-info/entry_points.txt
markpub_themes-2.1.2.dist-info/licenses/LICENSE
markpub_themes-2.1.2.dist-info/RECORD
