Metadata-Version: 2.4
Name: markpub-themes
Version: 2.1.2
Summary: Theme collection for markpub
Project-URL: Homepage, https://github.com/markpub/markpub-themes
Project-URL: Issues, https://github.com/markpub/markpub-themes/issues
Author-email: "William L. Anderson" <band@acm.org>
License-Expression: MIT
License-File: LICENSE
Keywords: markdown,markpub,publishing,themes
Classifier: Intended Audience :: Developers
Classifier: License :: OSI Approved :: MIT License
Classifier: Operating System :: OS Independent
Classifier: Programming Language :: Python :: 3
Classifier: Programming Language :: Python :: 3.12
Requires-Python: >=3.12
Requires-Dist: simple-term-menu>=1.6.6
